<?xml version='1.0' ?><data id="snapshot_xml1202" xmlns:h="http://www.w3.org/1999/xhtml" xmlns:jr="http://openrosa.org/javarosa" xmlns:xsd="http://www.w3.org/2001/XMLSchema" xmlns:ev="http://www.w3.org/2001/xml-events" xmlns:orx="http://openrosa.org/xforms" xmlns:odk="http://www.opendatakit.org/xforms"><start>2022-03-06T13:18:58.851+05:30</start><end>2022-03-06T13:20:01.080+05:30</end><group_vm6tx96><Date_of_Report>2022-03-06</Date_of_Report><Disability>Intellectual Disability</Disability></group_vm6tx96><District>Balangir_2</District><School>Dr. Harekrushna Mahatab Institute for Mentally Handicapped Managed by ASHRA, Balangir</School><group_ag1at83><Name>Ankita dash</Name><Designation>Project manager</Designation><Purpose_Of_Visit>To monitor</Purpose_Of_Visit><Whom_do_you_meet>Teacher School_Head</Whom_do_you_meet></group_ag1at83><group_yc0zy77><group_sa7sm10><Class_Age_Group>Pre-Primary (6 To 9)</Class_Age_Group><Chapter>Interpersonal Relationships</Chapter></group_sa7sm10><group_dm2ry23><Section>Building Harmonious Relationships</Section><Modality_Used>Yes</Modality_Used></group_dm2ry23></group_yc0zy77><group_yc0zy77><group_sa7sm10><Class_Age_Group>Secondary (13 To 15)</Class_Age_Group><Chapter>Reproductive Health anf HIV Prevention</Chapter></group_sa7sm10><group_dm2ry23><Section>HIV/AIDS</Section><Modality_Used>No</Modality_Used></group_dm2ry23></group_yc0zy77><group_mj26u68><Evaluators_Observation>Good going</Evaluators_Observation><Follow_up_Actions>No need</Follow_up_Actions><Image>1646552995350.jpg</Image></group_mj26u68><meta><instanceID>uuid:482cfe0c-a13a-4d4d-8a02-5007800533be</instanceID></meta></data>